material_igwn/__init__.py
material_igwn/_version.py
material_igwn/main.html
material_igwn/mkdocs_theme.yml
material_igwn/assets/images/favicon.ico
material_igwn/assets/images/kagra.png
material_igwn/assets/images/ligo.png
material_igwn/assets/images/logo.png
material_igwn/assets/images/lsc.png
material_igwn/assets/images/virgo.png
material_igwn/assets/stylesheets/igwn-mkdocs-material.css
material_igwn/partials/acknowledgements.html
material_igwn/partials/copyright.html
mkdocs_material_igwn-0.2.0.dist-info/METADATA
mkdocs_material_igwn-0.2.0.dist-info/WHEEL
mkdocs_material_igwn-0.2.0.dist-info/entry_points.txt
mkdocs_material_igwn-0.2.0.dist-info/top_level.txt
mkdocs_material_igwn-0.2.0.dist-info/RECORD
